blocksec2go_ethereum/__init__.py
blocksec2go_ethereum/_signer.py
blocksec2go_ethereum/_utils.py
blocksec2go_ethereum/exceptions.py
blocksec2go_ethereum-0.2.0.dist-info/LICENSE
blocksec2go_ethereum-0.2.0.dist-info/METADATA
blocksec2go_ethereum-0.2.0.dist-info/WHEEL
blocksec2go_ethereum-0.2.0.dist-info/top_level.txt
blocksec2go_ethereum-0.2.0.dist-info/RECORD
