Metadata-Version: 2.1
Name: blocksec2go-ethereum
Version: 0.2.0
Summary: Wrapper for blocksec2go allowing easy hardware-based signing of Ethereum transactions
Home-page: https://github.com/rexs-io/blocksec2go-ethereum
Author: rexs.io
Author-email: dev@rexs.io
License: ISC
Project-URL: Bug Reports, https://github.com/rexs-io/blocksec2go-ethereum/issues
Project-URL: Source, https://github.com/rexs-io/blocksec2go-ethereum
Keywords: ethereum blocksec2go hardware-signing hardware wallet
Platform: UNKNOWN
Classifier: Development Status :: 3 - Alpha
Classifier: Intended Audience :: Developers
Classifier: Topic :: Software Development :: Libraries
Classifier: License :: OSI Approved :: ISC License (ISCL)
Classifier: Programming Language :: Python :: 3
Requires-Python: >=3.0, <4
Requires-Dist: blocksec2go (==1.2)
Requires-Dist: ecdsa (==0.15)
Requires-Dist: web3 (==5.6.0)
